protein_interaction/__init__.py
protein_interaction/get_interaction.py
protein_interaction-0.0.1.dist-info/METADATA
protein_interaction-0.0.1.dist-info/WHEEL
protein_interaction-0.0.1.dist-info/top_level.txt
protein_interaction-0.0.1.dist-info/RECORD
