Metadata-Version: 2.1
Name: protein-interaction
Version: 0.0.1
Summary: Library for getting interactions of proteins
Author: Shiva Aryal
